[{"name":"Simulation","roi":{"DRAM":[{"AVG DBUS CONGESTED CYCLE":3.89188621706744,"RQ ROW_BUFFER_HIT":6314,"RQ ROW_BUFFER_MISS":30526,"WQ ROW_BUFFER_HIT":1230,"WQ ROW_BUFFER_MISS":3567}],"LLC":{"LOAD":{"hit":[5],"miss":[26977]},"PREFETCH":{"hit":[0],"miss":[0]},"RFO":{"hit":[0],"miss":[8211]},"TRANSLATION":{"hit":[24],"miss":[1658]},"WRITE":{"hit":[6828],"miss":[23]},"miss latency":619.9211261493396,"prefetch issued":0,"prefetch requested":0,"useful prefetch":0,"useless prefetch":0},"cores":[{"Avg ROB occupancy at mispredict":184.27807486631016,"cycles":4919793,"instructions":5000003,"mispredict":{"BRANCH_CONDITIONAL":184,"BRANCH_DIRECT_CALL":1,"BRANCH_DIRECT_JUMP":1,"BRANCH_INDIRECT":0,"BRANCH_INDIRECT_CALL":0,"BRANCH_RETURN":1}}],"cpu0_DTLB":{"LOAD":{"hit":[1082561],"miss":[90340]},"PREFETCH":{"hit":[0],"miss":[0]},"RFO":{"hit":[0],"miss":[0]},"TRANSLATION":{"hit":[0],"miss":[0]},"WRITE":{"hit":[0],"miss":[0]},"miss latency":25.490170467124198,"prefetch issued":0,"prefetch requested":0,"useful prefetch":0,"useless prefetch":0},"cpu0_ITLB":{"LOAD":{"hit":[741140],"miss":[8]},"PREFETCH":{"hit":[0],"miss":[0]},"RFO":{"hit":[0],"miss":[0]},"TRANSLATION":{"hit":[0],"miss":[0]},"WRITE":{"hit":[0],"miss":[0]},"miss latency":112.875,"prefetch issued":0,"prefetch requested":0,"useful prefetch":0,"useless prefetch":0},"cpu0_L1D":{"LOAD":{"hit":[1169903],"miss":[60769]},"PREFETCH":{"hit":[0],"miss":[0]},"RFO":{"hit":[0],"miss":[0]},"TRANSLATION":{"hit":[21943],"miss":[23963]},"WRITE":{"hit":[520701],"miss":[32624]},"miss latency":193.02696070077374,"prefetch issued":0,"prefetch requested":0,"useful prefetch":0,"useless prefetch":0},"cpu0_L1I":{"LOAD":{"hit":[965794],"miss":[67]},"PREFETCH":{"hit":[0],"miss":[0]},"RFO":{"hit":[0],"miss":[0]},"TRANSLATION":{"hit":[0],"miss":[0]},"WRITE":{"hit":[0],"miss":[0]},"miss latency":338.41791044776124,"prefetch issued":0,"prefetch requested":0,"useful prefetch":0,"useless prefetch":0},"cpu0_L2C":{"LOAD":{"hit":[26404],"miss":[26982]},"PREFETCH":{"hit":[0],"miss":[0]},"RFO":{"hit":[1859],"miss":[8214]},"TRANSLATION":{"hit":[22256],"miss":[1682]},"WRITE":{"hit":[10166],"miss":[45]},"miss latency":639.9838312163151,"prefetch issued":0,"prefetch requested":0,"useful prefetch":0,"useless prefetch":0},"cpu0_STLB":{"LOAD":{"hit":[40808],"miss":[24451]},"PREFETCH":{"hit":[0],"miss":[0]},"RFO":{"hit":[0],"miss":[0]},"TRANSLATION":{"hit":[0],"miss":[0]},"WRITE":{"hit":[0],"miss":[0]},"miss latency":87.03541777432416,"prefetch issued":0,"prefetch requested":0,"useful prefetch":0,"useless prefetch":0}},"sim":{"DRAM":[{"AVG DBUS CONGESTED CYCLE":3.89188621706744,"RQ ROW_BUFFER_HIT":6314,"RQ ROW_BUFFER_MISS":30526,"WQ ROW_BUFFER_HIT":1230,"WQ ROW_BUFFER_MISS":3567}],"LLC":{"LOAD":{"hit":[5],"miss":[26977]},"PREFETCH":{"hit":[0],"miss":[0]},"RFO":{"hit":[0],"miss":[8211]},"TRANSLATION":{"hit":[24],"miss":[1658]},"WRITE":{"hit":[6828],"miss":[23]},"miss latency":619.9211261493396,"prefetch issued":0,"prefetch requested":0,"useful prefetch":0,"useless prefetch":0},"cores":[{"Avg ROB occupancy at mispredict":184.27807486631016,"cycles":4919793,"instructions":5000003,"mispredict":{"BRANCH_CONDITIONAL":184,"BRANCH_DIRECT_CALL":1,"BRANCH_DIRECT_JUMP":1,"BRANCH_INDIRECT":0,"BRANCH_INDIRECT_CALL":0,"BRANCH_RETURN":1}}],"cpu0_DTLB":{"LOAD":{"hit":[1082561],"miss":[90340]},"PREFETCH":{"hit":[0],"miss":[0]},"RFO":{"hit":[0],"miss":[0]},"TRANSLATION":{"hit":[0],"miss":[0]},"WRITE":{"hit":[0],"miss":[0]},"miss latency":25.490170467124198,"prefetch issued":0,"prefetch requested":0,"useful prefetch":0,"useless prefetch":0},"cpu0_ITLB":{"LOAD":{"hit":[741140],"miss":[8]},"PREFETCH":{"hit":[0],"miss":[0]},"RFO":{"hit":[0],"miss":[0]},"TRANSLATION":{"hit":[0],"miss":[0]},"WRITE":{"hit":[0],"miss":[0]},"miss latency":112.875,"prefetch issued":0,"prefetch requested":0,"useful prefetch":0,"useless prefetch":0},"cpu0_L1D":{"LOAD":{"hit":[1169903],"miss":[60769]},"PREFETCH":{"hit":[0],"miss":[0]},"RFO":{"hit":[0],"miss":[0]},"TRANSLATION":{"hit":[21943],"miss":[23963]},"WRITE":{"hit":[520701],"miss":[32624]},"miss latency":193.02696070077374,"prefetch issued":0,"prefetch requested":0,"useful prefetch":0,"useless prefetch":0},"cpu0_L1I":{"LOAD":{"hit":[965794],"miss":[67]},"PREFETCH":{"hit":[0],"miss":[0]},"RFO":{"hit":[0],"miss":[0]},"TRANSLATION":{"hit":[0],"miss":[0]},"WRITE":{"hit":[0],"miss":[0]},"miss latency":338.41791044776124,"prefetch issued":0,"prefetch requested":0,"useful prefetch":0,"useless prefetch":0},"cpu0_L2C":{"LOAD":{"hit":[26404],"miss":[26982]},"PREFETCH":{"hit":[0],"miss":[0]},"RFO":{"hit":[1859],"miss":[8214]},"TRANSLATION":{"hit":[22256],"miss":[1682]},"WRITE":{"hit":[10166],"miss":[45]},"miss latency":639.9838312163151,"prefetch issued":0,"prefetch requested":0,"useful prefetch":0,"useless prefetch":0},"cpu0_STLB":{"LOAD":{"hit":[40808],"miss":[24451]},"PREFETCH":{"hit":[0],"miss":[0]},"RFO":{"hit":[0],"miss":[0]},"TRANSLATION":{"hit":[0],"miss":[0]},"WRITE":{"hit":[0],"miss":[0]},"miss latency":87.03541777432416,"prefetch issued":0,"prefetch requested":0,"useful prefetch":0,"useless prefetch":0}},"traces":["/scratch/cluster/hill/traces/spec2006/cactusADM_734B.trace.xz"]}]